ibalert/__init__.py
ibalert/admin.py
ibalert/apps.py
ibalert/asgi.py
ibalert/consumers.py
ibalert/models.py
ibalert/migrations/0001_initial.py
ibalert/migrations/0002_auto_20220131_0938.py
ibalert/migrations/0003_rename_usr_notifications_user.py
ibalert/migrations/0004_notifications_redirect.py
ibalert/migrations/__init__.py
ibalert-0.1.1.dist-info/LICENCE
ibalert-0.1.1.dist-info/METADATA
ibalert-0.1.1.dist-info/WHEEL
ibalert-0.1.1.dist-info/top_level.txt
ibalert-0.1.1.dist-info/RECORD
