Metadata-Version: 2.1
Name: ibalert
Version: 0.1.1
Summary: Notification/Alert for django users
Home-page: UNKNOWN
Author: Ideabreed Technology (Milann Malla)
Author-email: <hello@itsmilann.com>
License: UNKNOWN
Project-URL: channels-alert, https://github.com/ItsMilann/channels-alert/tree/release
Keywords: python,websocket,channels,python-alerts,ideabreed
Platform: UNKNOWN
Classifier: Development Status :: 1 - Planning
Classifier: Intended Audience :: Developers
Classifier: Programming Language :: Python :: 3.8
Classifier: Operating System :: Unix
Classifier: Operating System :: MacOS :: MacOS X
Classifier: Operating System :: Microsoft :: Windows
License-File: LICENCE
Requires-Dist: channels
Requires-Dist: channels-redis
Requires-Dist: coloredlogs
